pyinflect/AGIDReader.py
pyinflect/InflectionRules.py
pyinflect/Inflections.py
pyinflect/__init__.py
pyinflect/infl.csv
pyinflect/overrides.csv
pyinflect-0.5.1.dist-info/LICENSE
pyinflect-0.5.1.dist-info/METADATA
pyinflect-0.5.1.dist-info/WHEEL
pyinflect-0.5.1.dist-info/top_level.txt
pyinflect-0.5.1.dist-info/RECORD
