Metadata-Version: 2.1
Name: pyinflect
Version: 0.5.1
Summary: A python module for word inflections designed for use with Spacy.
Home-page: https://github.com/bjascob/pyinflect
Author: Brad Jascob
Author-email: bjascob@msn.com
License: UNKNOWN
Platform: UNKNOWN
Classifier: Programming Language :: Python :: 2
Classifier: Programming Language :: Python :: 3
Classifier: License :: OSI Approved :: MIT License
Classifier: Operating System :: OS Independent
